{
  "id": "Personal Blog/Kubernetes/StatefulSets",
  "title": "Deployment and StatefulSet",
  "description": "Similarities and Differences",
  "source": "@site/docs/Personal Blog/Kubernetes/StatefulSets.md",
  "sourceDirName": "Personal Blog/Kubernetes",
  "slug": "/Personal Blog/Kubernetes/StatefulSets",
  "permalink": "/docs/Personal Blog/Kubernetes/StatefulSets",
  "draft": false,
  "unlisted": false,
  "editUrl": "https://github.com/divyn/divyn.github.io/edit/main/docs/Personal Blog/Kubernetes/StatefulSets.md",
  "tags": [],
  "version": "current",
  "frontMatter": {
    "layout": "default",
    "title": "Deployment and StatefulSet",
    "parent": "Kubernetes"
  },
  "sidebar": "tutorialSidebar",
  "previous": {
    "title": "Services",
    "permalink": "/docs/Personal Blog/Kubernetes/ServicesCoreConcepts"
  },
  "next": {
    "title": "Storage Classes",
    "permalink": "/docs/Personal Blog/Kubernetes/StorageClasses"
  }
}