{
  "entrypoints": [
    "main"
  ],
  "origins": {
    "3042": [
      3042
    ],
    "4132": [
      6651,
      9396,
      4132
    ],
    "6733": [
      1869,
      6061,
      8401,
      6733
    ],
    "10091836": [
      5569
    ],
    "10535974": [
      2259
    ],
    "17896441": [
      1869,
      6733,
      8401
    ],
    "main": [
      1869,
      5354,
      8792
    ],
    "runtime~main": [
      1869,
      8792,
      5354
    ],
    "0058b4c6": [
      849
    ],
    "0311a412": [
      2696
    ],
    "09b2f754": [
      1684
    ],
    "0e384e19": [
      3976
    ],
    "14eb3368": [
      1869,
      6969
    ],
    "1c7fbca6": [
      7044
    ],
    "1f391b9e": [
      1869,
      6733,
      6061
    ],
    "28d80fa9": [
      1173
    ],
    "2b737e34": [
      2568
    ],
    "2dd9f6c3": [
      6234
    ],
    "3720c009": [
      1869,
      4787
    ],
    "3785a73c": [
      8894
    ],
    "393be207": [
      4134
    ],
    "3ca760b4": [
      3985
    ],
    "3d8cfb60": [
      4839
    ],
    "3e48b81a": [
      4319
    ],
    "42491c92": [
      5581
    ],
    "428e5996": [
      4899
    ],
    "42f9cdda": [
      1266
    ],
    "4846f15a": [
      6772
    ],
    "4aa9084f": [
      4190
    ],
    "4bfbb8e0": [
      2576
    ],
    "5795d7fb": [
      5378
    ],
    "5ae647a4": [
      9344
    ],
    "5b6273c2": [
      499
    ],
    "5e95c892": [
      9647
    ],
    "60adb665": [
      8189
    ],
    "7462b381": [
      5358
    ],
    "78ffbc39": [
      4132,
      6651
    ],
    "7945fcef": [
      182
    ],
    "7c0175fa": [
      7583
    ],
    "7f666d96": [
      1291
    ],
    "880664e3": [
      9495
    ],
    "898514b1": [
      9067
    ],
    "89a3ed9c": [
      7217
    ],
    "937b3cea": [
      6956
    ],
    "9bbc827e": [
      8177
    ],
    "a05acee0": [
      3801
    ],
    "a7456010": [
      1235
    ],
    "a7bd4aaa": [
      7098
    ],
    "a94703ab": [
      1869,
      9048
    ],
    "aba21aa0": [
      5742
    ],
    "ae3a9f7f": [
      7627
    ],
    "b52fb840": [
      6410
    ],
    "bbbf3c3c": [
      7191
    ],
    "c4f5d8e4": [
      1869,
      2634
    ],
    "cbff8233": [
      8008
    ],
    "ce95f7db": [
      1462
    ],
    "db9fde0b": [
      4371
    ],
    "df203c0f": [
      1869,
      4279
    ],
    "e61d732c": [
      962
    ],
    "ef19aac5": [
      7690
    ],
    "f550e0c1": [
      6332
    ],
    "f5cba81c": [
      4132,
      9396
    ],
    "reactPlayerYouTube": [
      8446
    ],
    "reactPlayerSoundCloud": [
      9979
    ],
    "reactPlayerVimeo": [
      6173
    ],
    "reactPlayerMux": [
      2723
    ],
    "reactPlayerFacebook": [
      6887
    ],
    "reactPlayerStreamable": [
      8
    ],
    "reactPlayerWistia": [
      9340
    ],
    "reactPlayerTwitch": [
      2042
    ],
    "reactPlayerDailyMotion": [
      6328
    ],
    "reactPlayerMixcloud": [
      7570
    ],
    "reactPlayerVidyard": [
      3392
    ],
    "reactPlayerKaltura": [
      6463
    ],
    "reactPlayerFilePlayer": [
      7458
    ],
    "reactPlayerPreview": [
      6353
    ],
    "styles": [
      2634,
      4279,
      4787,
      5354,
      6061,
      6733,
      6969,
      8401,
      8792,
      9048,
      1869
    ]
  },
  "assets": {
    "8": {
      "js": [
        {
          "file": "assets/js/reactPlayerStreamable.e5bda3a8.js",
          "hash": "d72bd5324275e2ac",
          "publicPath": "/assets/js/reactPlayerStreamable.e5bda3a8.js"
        }
      ]
    },
    "182": {
      "js": [
        {
          "file": "assets/js/7945fcef.d0b6a7d3.js",
          "hash": "25bca989c5888174",
          "publicPath": "/assets/js/7945fcef.d0b6a7d3.js"
        }
      ]
    },
    "499": {
      "js": [
        {
          "file": "assets/js/5b6273c2.dd678b49.js",
          "hash": "8dc7b25a8858c6fe",
          "publicPath": "/assets/js/5b6273c2.dd678b49.js"
        }
      ]
    },
    "849": {
      "js": [
        {
          "file": "assets/js/0058b4c6.7cfe8d66.js",
          "hash": "9b62632be9b627e5",
          "publicPath": "/assets/js/0058b4c6.7cfe8d66.js"
        }
      ]
    },
    "962": {
      "js": [
        {
          "file": "assets/js/e61d732c.ca2860a9.js",
          "hash": "a681ed1b0fe5cace",
          "publicPath": "/assets/js/e61d732c.ca2860a9.js"
        }
      ]
    },
    "1173": {
      "js": [
        {
          "file": "assets/js/28d80fa9.492ecd25.js",
          "hash": "72c62a62c9b1554d",
          "publicPath": "/assets/js/28d80fa9.492ecd25.js"
        }
      ]
    },
    "1235": {
      "js": [
        {
          "file": "assets/js/a7456010.437112ee.js",
          "hash": "1900c6cda8daab2e",
          "publicPath": "/assets/js/a7456010.437112ee.js"
        }
      ]
    },
    "1266": {
      "js": [
        {
          "file": "assets/js/42f9cdda.939a0aaa.js",
          "hash": "3863c57f98ce262d",
          "publicPath": "/assets/js/42f9cdda.939a0aaa.js"
        }
      ]
    },
    "1291": {
      "js": [
        {
          "file": "assets/js/7f666d96.b618541c.js",
          "hash": "cfa8eaea766262c6",
          "publicPath": "/assets/js/7f666d96.b618541c.js"
        }
      ]
    },
    "1462": {
      "js": [
        {
          "file": "assets/js/ce95f7db.91d9a533.js",
          "hash": "b616042d50d4640d",
          "publicPath": "/assets/js/ce95f7db.91d9a533.js"
        }
      ]
    },
    "1684": {
      "js": [
        {
          "file": "assets/js/09b2f754.1f2d3046.js",
          "hash": "9210d596f7554a01",
          "publicPath": "/assets/js/09b2f754.1f2d3046.js"
        }
      ]
    },
    "1869": {
      "css": [
        {
          "file": "assets/css/styles.4dcd5ca2.css",
          "hash": "02f44b6064923469",
          "publicPath": "/assets/css/styles.4dcd5ca2.css"
        }
      ]
    },
    "2042": {
      "js": [
        {
          "file": "assets/js/reactPlayerTwitch.44c8e262.js",
          "hash": "2d3d56efa579beda",
          "publicPath": "/assets/js/reactPlayerTwitch.44c8e262.js"
        }
      ]
    },
    "2259": {
      "js": [
        {
          "file": "assets/js/10535974.7519d085.js",
          "hash": "85a2b714150a551e",
          "publicPath": "/assets/js/10535974.7519d085.js"
        }
      ]
    },
    "2568": {
      "js": [
        {
          "file": "assets/js/2b737e34.02ff3f84.js",
          "hash": "cca44354354b4c05",
          "publicPath": "/assets/js/2b737e34.02ff3f84.js"
        }
      ]
    },
    "2576": {
      "js": [
        {
          "file": "assets/js/4bfbb8e0.9c9f5b42.js",
          "hash": "f24bc4bdb823eed0",
          "publicPath": "/assets/js/4bfbb8e0.9c9f5b42.js"
        }
      ]
    },
    "2634": {
      "js": [
        {
          "file": "assets/js/c4f5d8e4.f3c34b98.js",
          "hash": "01a3ad10bcef6291",
          "publicPath": "/assets/js/c4f5d8e4.f3c34b98.js"
        }
      ]
    },
    "2696": {
      "js": [
        {
          "file": "assets/js/0311a412.551deb4f.js",
          "hash": "922216294ffefdd7",
          "publicPath": "/assets/js/0311a412.551deb4f.js"
        }
      ]
    },
    "2723": {
      "js": [
        {
          "file": "assets/js/reactPlayerMux.44338e06.js",
          "hash": "1c58ebdd5c18aadd",
          "publicPath": "/assets/js/reactPlayerMux.44338e06.js"
        }
      ]
    },
    "3042": {
      "js": [
        {
          "file": "assets/js/3042.2dea597f.js",
          "hash": "9041c1906ed0bd65",
          "publicPath": "/assets/js/3042.2dea597f.js"
        }
      ]
    },
    "3392": {
      "js": [
        {
          "file": "assets/js/reactPlayerVidyard.554e4aab.js",
          "hash": "947f6b3909856a4d",
          "publicPath": "/assets/js/reactPlayerVidyard.554e4aab.js"
        }
      ]
    },
    "3801": {
      "js": [
        {
          "file": "assets/js/a05acee0.bac5f72f.js",
          "hash": "6a80aea410521a69",
          "publicPath": "/assets/js/a05acee0.bac5f72f.js"
        }
      ]
    },
    "3976": {
      "js": [
        {
          "file": "assets/js/0e384e19.0d053f70.js",
          "hash": "50f306102564f044",
          "publicPath": "/assets/js/0e384e19.0d053f70.js"
        }
      ]
    },
    "3985": {
      "js": [
        {
          "file": "assets/js/3ca760b4.002b4f76.js",
          "hash": "cf8970ea6f9164e0",
          "publicPath": "/assets/js/3ca760b4.002b4f76.js"
        }
      ]
    },
    "4132": {
      "js": [
        {
          "file": "assets/js/4132.80ebdd7f.js",
          "hash": "3ae85f9a2f4fb044",
          "publicPath": "/assets/js/4132.80ebdd7f.js"
        }
      ]
    },
    "4134": {
      "js": [
        {
          "file": "assets/js/393be207.0b27782e.js",
          "hash": "c94c3c346d940fee",
          "publicPath": "/assets/js/393be207.0b27782e.js"
        }
      ]
    },
    "4190": {
      "js": [
        {
          "file": "assets/js/4aa9084f.edf59a48.js",
          "hash": "2aa26c9e10de1602",
          "publicPath": "/assets/js/4aa9084f.edf59a48.js"
        }
      ]
    },
    "4279": {
      "js": [
        {
          "file": "assets/js/df203c0f.b21b52a7.js",
          "hash": "e44bc0e837b286e5",
          "publicPath": "/assets/js/df203c0f.b21b52a7.js"
        }
      ]
    },
    "4319": {
      "js": [
        {
          "file": "assets/js/3e48b81a.89c6be68.js",
          "hash": "ed3b181f23506ea8",
          "publicPath": "/assets/js/3e48b81a.89c6be68.js"
        }
      ]
    },
    "4371": {
      "js": [
        {
          "file": "assets/js/db9fde0b.a469718f.js",
          "hash": "e57440015cdfd2a7",
          "publicPath": "/assets/js/db9fde0b.a469718f.js"
        }
      ]
    },
    "4787": {
      "js": [
        {
          "file": "assets/js/3720c009.bb5302d7.js",
          "hash": "e81c05912c2ce4d8",
          "publicPath": "/assets/js/3720c009.bb5302d7.js"
        }
      ]
    },
    "4839": {
      "js": [
        {
          "file": "assets/js/3d8cfb60.79edb28d.js",
          "hash": "c5dbbf80d2ceb99b",
          "publicPath": "/assets/js/3d8cfb60.79edb28d.js"
        }
      ]
    },
    "4899": {
      "js": [
        {
          "file": "assets/js/428e5996.4f4a284c.js",
          "hash": "2900fe9bddc513ae",
          "publicPath": "/assets/js/428e5996.4f4a284c.js"
        }
      ]
    },
    "5354": {
      "js": [
        {
          "file": "assets/js/runtime~main.eb8c594e.js",
          "hash": "c9f62dcf3ff4352b",
          "publicPath": "/assets/js/runtime~main.eb8c594e.js"
        }
      ]
    },
    "5358": {
      "js": [
        {
          "file": "assets/js/7462b381.f95e251e.js",
          "hash": "12522b3466579c3c",
          "publicPath": "/assets/js/7462b381.f95e251e.js"
        }
      ]
    },
    "5378": {
      "js": [
        {
          "file": "assets/js/5795d7fb.442a958c.js",
          "hash": "585202ae63bb3bea",
          "publicPath": "/assets/js/5795d7fb.442a958c.js"
        }
      ]
    },
    "5569": {
      "js": [
        {
          "file": "assets/js/10091836.e1d5b922.js",
          "hash": "94e3c5576258ee77",
          "publicPath": "/assets/js/10091836.e1d5b922.js"
        }
      ]
    },
    "5581": {
      "js": [
        {
          "file": "assets/js/42491c92.1f9f7638.js",
          "hash": "f6b830a21ce7ea2b",
          "publicPath": "/assets/js/42491c92.1f9f7638.js"
        }
      ]
    },
    "5742": {
      "js": [
        {
          "file": "assets/js/aba21aa0.c7cab3d2.js",
          "hash": "a56d117795ed4d04",
          "publicPath": "/assets/js/aba21aa0.c7cab3d2.js"
        }
      ]
    },
    "6061": {
      "js": [
        {
          "file": "assets/js/1f391b9e.df10d82f.js",
          "hash": "bfefa614b573d5c0",
          "publicPath": "/assets/js/1f391b9e.df10d82f.js"
        }
      ]
    },
    "6173": {
      "js": [
        {
          "file": "assets/js/reactPlayerVimeo.cbe3612b.js",
          "hash": "aed1def3bc1377c2",
          "publicPath": "/assets/js/reactPlayerVimeo.cbe3612b.js"
        }
      ]
    },
    "6234": {
      "js": [
        {
          "file": "assets/js/2dd9f6c3.9ef972ab.js",
          "hash": "367a4030df09051e",
          "publicPath": "/assets/js/2dd9f6c3.9ef972ab.js"
        }
      ]
    },
    "6328": {
      "js": [
        {
          "file": "assets/js/reactPlayerDailyMotion.5ec10482.js",
          "hash": "2b49f4a2f9d408a4",
          "publicPath": "/assets/js/reactPlayerDailyMotion.5ec10482.js"
        }
      ]
    },
    "6332": {
      "js": [
        {
          "file": "assets/js/f550e0c1.993f9b04.js",
          "hash": "f2a420f6dc22af92",
          "publicPath": "/assets/js/f550e0c1.993f9b04.js"
        }
      ]
    },
    "6353": {
      "js": [
        {
          "file": "assets/js/reactPlayerPreview.6fbd249f.js",
          "hash": "9f37e20b14f0699f",
          "publicPath": "/assets/js/reactPlayerPreview.6fbd249f.js"
        }
      ]
    },
    "6410": {
      "js": [
        {
          "file": "assets/js/b52fb840.bef314b3.js",
          "hash": "a6e79da7e94fb08f",
          "publicPath": "/assets/js/b52fb840.bef314b3.js"
        }
      ]
    },
    "6463": {
      "js": [
        {
          "file": "assets/js/reactPlayerKaltura.50e69653.js",
          "hash": "6758ef7a72ea5fda",
          "publicPath": "/assets/js/reactPlayerKaltura.50e69653.js"
        }
      ]
    },
    "6651": {
      "js": [
        {
          "file": "assets/js/78ffbc39.4c88ddfa.js",
          "hash": "5e900683e8ed7968",
          "publicPath": "/assets/js/78ffbc39.4c88ddfa.js"
        }
      ]
    },
    "6733": {
      "js": [
        {
          "file": "assets/js/6733.1dfe019f.js",
          "hash": "6af6fd39e44e84b0",
          "publicPath": "/assets/js/6733.1dfe019f.js"
        }
      ]
    },
    "6772": {
      "js": [
        {
          "file": "assets/js/4846f15a.325de8c7.js",
          "hash": "4e6b263a59c10938",
          "publicPath": "/assets/js/4846f15a.325de8c7.js"
        }
      ]
    },
    "6887": {
      "js": [
        {
          "file": "assets/js/reactPlayerFacebook.f2f762e9.js",
          "hash": "d9a481ddef840416",
          "publicPath": "/assets/js/reactPlayerFacebook.f2f762e9.js"
        }
      ]
    },
    "6956": {
      "js": [
        {
          "file": "assets/js/937b3cea.5247f35b.js",
          "hash": "eeb74eed5b14cea0",
          "publicPath": "/assets/js/937b3cea.5247f35b.js"
        }
      ]
    },
    "6969": {
      "js": [
        {
          "file": "assets/js/14eb3368.dc9ff4dc.js",
          "hash": "9cd3ec6704068f25",
          "publicPath": "/assets/js/14eb3368.dc9ff4dc.js"
        }
      ]
    },
    "7044": {
      "js": [
        {
          "file": "assets/js/1c7fbca6.ae77766d.js",
          "hash": "d4aef443850989fa",
          "publicPath": "/assets/js/1c7fbca6.ae77766d.js"
        }
      ]
    },
    "7098": {
      "js": [
        {
          "file": "assets/js/a7bd4aaa.b7d6829f.js",
          "hash": "4d92cdfa582effe5",
          "publicPath": "/assets/js/a7bd4aaa.b7d6829f.js"
        }
      ]
    },
    "7191": {
      "js": [
        {
          "file": "assets/js/bbbf3c3c.144eff13.js",
          "hash": "6d53aaef3040d111",
          "publicPath": "/assets/js/bbbf3c3c.144eff13.js"
        }
      ]
    },
    "7217": {
      "js": [
        {
          "file": "assets/js/89a3ed9c.427a8404.js",
          "hash": "97ad81296f15be78",
          "publicPath": "/assets/js/89a3ed9c.427a8404.js"
        }
      ]
    },
    "7458": {
      "js": [
        {
          "file": "assets/js/reactPlayerFilePlayer.1d7ba038.js",
          "hash": "c54a7566bc891172",
          "publicPath": "/assets/js/reactPlayerFilePlayer.1d7ba038.js"
        }
      ]
    },
    "7570": {
      "js": [
        {
          "file": "assets/js/reactPlayerMixcloud.ac10aedd.js",
          "hash": "52de85a3b6c9e6d9",
          "publicPath": "/assets/js/reactPlayerMixcloud.ac10aedd.js"
        }
      ]
    },
    "7583": {
      "js": [
        {
          "file": "assets/js/7c0175fa.eb9a9b7b.js",
          "hash": "3d4573b561ceea81",
          "publicPath": "/assets/js/7c0175fa.eb9a9b7b.js"
        }
      ]
    },
    "7627": {
      "js": [
        {
          "file": "assets/js/ae3a9f7f.4d6c082d.js",
          "hash": "7181ebf3af1c5534",
          "publicPath": "/assets/js/ae3a9f7f.4d6c082d.js"
        }
      ]
    },
    "7690": {
      "js": [
        {
          "file": "assets/js/ef19aac5.8fcc896d.js",
          "hash": "e92f5988273eb801",
          "publicPath": "/assets/js/ef19aac5.8fcc896d.js"
        }
      ]
    },
    "8008": {
      "js": [
        {
          "file": "assets/js/cbff8233.c1f1866a.js",
          "hash": "b7a6711b61f7a826",
          "publicPath": "/assets/js/cbff8233.c1f1866a.js"
        }
      ]
    },
    "8177": {
      "js": [
        {
          "file": "assets/js/9bbc827e.2224d143.js",
          "hash": "f0e629f494aaf2af",
          "publicPath": "/assets/js/9bbc827e.2224d143.js"
        }
      ]
    },
    "8189": {
      "js": [
        {
          "file": "assets/js/60adb665.6b58ff28.js",
          "hash": "48f461eb12b70b3d",
          "publicPath": "/assets/js/60adb665.6b58ff28.js"
        }
      ]
    },
    "8401": {
      "js": [
        {
          "file": "assets/js/17896441.6d65fcb9.js",
          "hash": "bcb472d77a3fa838",
          "publicPath": "/assets/js/17896441.6d65fcb9.js"
        }
      ]
    },
    "8446": {
      "js": [
        {
          "file": "assets/js/reactPlayerYouTube.4ce0039d.js",
          "hash": "c45259edafe2d2a3",
          "publicPath": "/assets/js/reactPlayerYouTube.4ce0039d.js"
        }
      ]
    },
    "8792": {
      "js": [
        {
          "file": "assets/js/main.4b9cbcdb.js",
          "hash": "ce8a2296654ff9fe",
          "publicPath": "/assets/js/main.4b9cbcdb.js"
        }
      ]
    },
    "8894": {
      "js": [
        {
          "file": "assets/js/3785a73c.88531d86.js",
          "hash": "bef3a1eeb317cf88",
          "publicPath": "/assets/js/3785a73c.88531d86.js"
        }
      ]
    },
    "9048": {
      "js": [
        {
          "file": "assets/js/a94703ab.9b0b0d68.js",
          "hash": "eb5f7ca76d3a7936",
          "publicPath": "/assets/js/a94703ab.9b0b0d68.js"
        }
      ]
    },
    "9067": {
      "js": [
        {
          "file": "assets/js/898514b1.358805a8.js",
          "hash": "06c20814153199da",
          "publicPath": "/assets/js/898514b1.358805a8.js"
        }
      ]
    },
    "9340": {
      "js": [
        {
          "file": "assets/js/reactPlayerWistia.af225d0b.js",
          "hash": "22193cf8fd73c41e",
          "publicPath": "/assets/js/reactPlayerWistia.af225d0b.js"
        }
      ]
    },
    "9344": {
      "js": [
        {
          "file": "assets/js/5ae647a4.43edf3c6.js",
          "hash": "768c0b78745fefd8",
          "publicPath": "/assets/js/5ae647a4.43edf3c6.js"
        }
      ]
    },
    "9396": {
      "js": [
        {
          "file": "assets/js/f5cba81c.b84b3eb3.js",
          "hash": "90325798fed2745a",
          "publicPath": "/assets/js/f5cba81c.b84b3eb3.js"
        }
      ]
    },
    "9495": {
      "js": [
        {
          "file": "assets/js/880664e3.0d28182e.js",
          "hash": "5b34e18c936fc129",
          "publicPath": "/assets/js/880664e3.0d28182e.js"
        }
      ]
    },
    "9647": {
      "js": [
        {
          "file": "assets/js/5e95c892.066a4cfe.js",
          "hash": "3090c717e4490e88",
          "publicPath": "/assets/js/5e95c892.066a4cfe.js"
        }
      ]
    },
    "9979": {
      "js": [
        {
          "file": "assets/js/reactPlayerSoundCloud.853999f9.js",
          "hash": "c635a381a97be66d",
          "publicPath": "/assets/js/reactPlayerSoundCloud.853999f9.js"
        }
      ]
    }
  }
}